LICENSE
README.md
setup.py
vaassdk/__init__.py
vaassdk.egg-info/PKG-INFO
vaassdk.egg-info/SOURCES.txt
vaassdk.egg-info/dependency_links.txt
vaassdk.egg-info/top_level.txt
vaassdk/example/__init__.py
vaassdk/example/demo_report.py
vaassdk/example/demo_vaas.py
vaassdk/src/__init__.py
vaassdk/src/vaas/__init__.py
vaassdk/src/vaas/config.py
vaassdk/src/vaas/credentials.py
vaassdk/src/vaas/report.py
vaassdk/src/vaas/tools.py
vaassdk/src/vaas/vaas.py