Metadata-Version: 1.0
Name: vaassdk
Version: 1.0.7
Summary: vaassdk
Home-page: https://github.com/yilanyun/vaas-sdk-python.git
Author: yilan
Author-email: UNKNOWN
License: UNKNOWN
Platform: UNKNOWN
